pycarbontracer/__init__.py
pycarbontracer/classes/__init__.py
pycarbontracer/classes/carbontracer.py
pycarbontracer/classes/http.py
pycarbontracer-0.9.1.dist-info/METADATA
pycarbontracer-0.9.1.dist-info/WHEEL
pycarbontracer-0.9.1.dist-info/licenses/LICENSE
pycarbontracer-0.9.1.dist-info/RECORD
