Metadata-Version: 2.1
Name: pycarbontracer
Version: 0.9.1
Summary: Simple Python wrapper to fetch data from CarbonTracer (carbontracer.uni-graz.at)
Project-URL: Homepage, https://kumig.it/kumitterer/pycarbontracer
Project-URL: Bug Tracker, https://kumig.it/kumitterer/pycarbontracer/issues
Author-email: Kumi Mitterer <pycarbontracer@kumi.email>
License: Copyright (c) 2023 Kumi Mitterer <pycarbontracer@kumi.email>
License-File: LICENSE
Classifier: License :: OSI Approved :: MIT License
Classifier: Operating System :: OS Independent
Classifier: Programming Language :: Python :: 3
Requires-Python: >=3.10
